{
    "$schema": "https://json-schema.org/draft/2020-12/schema",
    "$id": "https://raw.githubusercontent.com/tryterra/openapi/refs/heads/v5-update/schemas/DeviceDataType.json",
    "type": "string",
    "enum": [
        "STEPS",
        "ACTIVE_MINUTES",
        "BMR",
        "CALORIES",
        "DISTANCE",
        "HEART_RATE",
        "OXYGEN_SATURATION",
        "SLEEP_TYPE",
        "SPEED",
        "CADENCE"
    ],
    "description": "Represents data types that a certain device contributed to."
}